INSTALL.rst
LICENSE.rst
MANIFEST.in
README.rst
requirements.txt
setup.py
csb/__init__.py
csb/build.py
csb.egg-info/PKG-INFO
csb.egg-info/SOURCES.txt
csb.egg-info/dependency_links.txt
csb.egg-info/entry_points.txt
csb.egg-info/requires.txt
csb.egg-info/top_level.txt
csb/apps/__init__.py
csb/apps/bfit.py
csb/apps/bfite.py
csb/apps/buildhmm.py
csb/apps/csfrag.py
csb/apps/embd.py
csb/apps/helloworld.py
csb/apps/hhfrag.py
csb/apps/hhsearch.py
csb/apps/precision.py
csb/apps/promix.py
csb/bio/__init__.py
csb/bio/fragments/__init__.py
csb/bio/fragments/rosetta.py
csb/bio/hmm/__init__.py
csb/bio/hmm/pseudocounts.py
csb/bio/io/__init__.py
csb/bio/io/clans.py
csb/bio/io/cs.py
csb/bio/io/dssp.py
csb/bio/io/fasta.py
csb/bio/io/hhpred.py
csb/bio/io/mrc.py
csb/bio/io/noe.py
csb/bio/io/procheck.py
csb/bio/io/psipred.py
csb/bio/io/svg.py
csb/bio/io/vasco.py
csb/bio/io/whatif.py
csb/bio/io/wwpdb.py
csb/bio/nmr/__init__.py
csb/bio/nmr/resources/AtomConnectivity.xml
csb/bio/nmr/resources/RandomCoil.Corrections.tsv
csb/bio/nmr/resources/RandomCoil.Reference.tsv
csb/bio/sequence/__init__.py
csb/bio/sequence/alignment.py
csb/bio/structure/__init__.py
csb/bio/utils/__init__.py
csb/core/__init__.py
csb/io/__init__.py
csb/io/plots.py
csb/io/tsv.py
csb/numeric/__init__.py
csb/numeric/integrators.py
csb/statistics/__init__.py
csb/statistics/ars.py
csb/statistics/maxent.py
csb/statistics/mixtures.py
csb/statistics/rand.py
csb/statistics/scalemixture.py
csb/statistics/pdf/__init__.py
csb/statistics/pdf/parameterized.py
csb/statistics/samplers/__init__.py
csb/statistics/samplers/mc/__init__.py
csb/statistics/samplers/mc/multichain.py
csb/statistics/samplers/mc/neqsteppropagator.py
csb/statistics/samplers/mc/propagators.py
csb/statistics/samplers/mc/singlechain.py
csb/statmech/__init__.py
csb/statmech/ensembles.py
csb/statmech/wham.py
csb/test/__init__.py
csb/test/app.py
csb/test/cases/__init__.py
csb/test/cases/bio/__init__.py
csb/test/cases/bio/fragments/__init__.py
csb/test/cases/bio/hmm/__init__.py
csb/test/cases/bio/io/__init__.py
csb/test/cases/bio/io/clans/__init__.py
csb/test/cases/bio/io/cs/__init__.py
csb/test/cases/bio/io/fasta/__init__.py
